mobile_strings_converter/__init__.py
mobile_strings_converter/__main__.py
mobile_strings_converter/assets/fonts/Aakar.ttf
"mobile_strings_converter/assets/fonts/AnekTelugu-VariableFont_wdth,wght.ttf"
mobile_strings_converter/assets/fonts/DejaVuSansCondensed.ttf
mobile_strings_converter/assets/fonts/Eunjin.ttf
mobile_strings_converter/assets/fonts/Gurvetica_a8_Heavy.ttf
mobile_strings_converter/assets/fonts/Latha.ttf
mobile_strings_converter/assets/fonts/Waree.ttf
mobile_strings_converter/assets/fonts/fireflysung.ttf
mobile_strings_converter/assets/fonts/gargi.ttf
mobile_strings_converter/console_style.py
mobile_strings_converter/converter.py
mobile_strings_converter-0.1.4.dist-info/LICENSE
mobile_strings_converter-0.1.4.dist-info/METADATA
mobile_strings_converter-0.1.4.dist-info/WHEEL
mobile_strings_converter-0.1.4.dist-info/RECORD
