Metadata-Version: 2.1
Name: mobile-strings-converter
Version: 0.1.4
Summary: Convert Android & iOS strings files to any supported file type and vice versa.
Home-page: https://github.com/HenestrosaDev/mobile-strings-converter
License: MIT
Keywords: android,strings.xml,strings,converter,csv,xlsx,yaml,html,json,ods,pdf,md,ios,Localizable.strings
Author: José Carlos López
Author-email: henestrosadev@gmail.com
Requires-Python: >=3.8
Classifier: Environment :: Console
Classifier: Intended Audience :: Developers
Classifier: License :: OSI Approved :: MIT License
Classifier: Operating System :: MacOS
Classifier: Operating System :: Microsoft :: Windows
Classifier: Operating System :: OS Independent
Classifier: Operating System :: Other OS
Classifier: Operating System :: POSIX :: Linux
Classifier: Programming Language :: Python :: 3
Classifier: Programming Language :: Python :: 3.8
Classifier: Programming Language :: Python :: 3.9
Classifier: Programming Language :: Python :: 3.10
Classifier: Programming Language :: Python :: 3.11
Classifier: Programming Language :: Python :: 3.12
Classifier: Topic :: Text Processing :: General
Classifier: Topic :: Utilities
Requires-Dist: arabic-reshaper (>=3.0.0,<4.0.0)
Requires-Dist: ezodf (>=0.3.2,<0.4.0)
Requires-Dist: fpdf2 (>=2.7.8,<3.0.0)
Requires-Dist: gspread (>=6.1.0,<7.0.0)
Requires-Dist: lingua-language-detector (>=2.0.2,<3.0.0)
Requires-Dist: lxml (>=5.2.2,<6.0.0)
Requires-Dist: openpyxl (>=3.1.2,<4.0.0)
Requires-Dist: protobuf (>=5.26.1,<6.0.0)
Requires-Dist: pypdf2 (>=3.0.1,<4.0.0)
Requires-Dist: python-bidi (>=0.4.2,<0.5.0)
Requires-Dist: pyyaml (>=6.0.1,<7.0.0)
Project-URL: Repository, https://github.com/HenestrosaDev/mobile-strings-converter
